MANIFEST.in
README.md
setup.cfg
setup.py
VGMPlay/ChipMapper.c
VGMPlay/ChipMapper.h
VGMPlay/PortTalk_IOCTL.h
VGMPlay/Stream.c
VGMPlay/Stream.h
VGMPlay/VGMFile.h
VGMPlay/VGMPlay.c
VGMPlay/VGMPlay.h
VGMPlay/VGMPlayUI.c
VGMPlay/VGMPlay_AddFmts.c
VGMPlay/VGMPlay_Intf.h
VGMPlay/libvgm.c
VGMPlay/libvgm.h
VGMPlay/pt_ioctl.c
VGMPlay/stdbool.h
VGMPlay/vgm2pcm.c
VGMPlay/vgm2wav.c
VGMPlay/XMasFiles/SWJ-SQRC01_1C.h
VGMPlay/XMasFiles/XMasBonus.h
VGMPlay/chips/2151intf.c
VGMPlay/chips/2151intf.h
VGMPlay/chips/2203intf.c
VGMPlay/chips/2203intf.h
VGMPlay/chips/2413intf.c
VGMPlay/chips/2413intf.h
VGMPlay/chips/2413tone.h
VGMPlay/chips/2608intf.c
VGMPlay/chips/2608intf.h
VGMPlay/chips/2610intf.c
VGMPlay/chips/2610intf.h
VGMPlay/chips/2612intf.c
VGMPlay/chips/2612intf.h
VGMPlay/chips/262intf.c
VGMPlay/chips/262intf.h
VGMPlay/chips/281btone.h
VGMPlay/chips/3526intf.c
VGMPlay/chips/3526intf.h
VGMPlay/chips/3812intf.c
VGMPlay/chips/3812intf.h
VGMPlay/chips/8950intf.c
VGMPlay/chips/8950intf.h
VGMPlay/chips/ChipIncl.h
VGMPlay/chips/Ootake_PSG.c
VGMPlay/chips/Ootake_PSG.h
VGMPlay/chips/adlibemu.h
VGMPlay/chips/adlibemu_opl2.c
VGMPlay/chips/adlibemu_opl3.c
VGMPlay/chips/ay8910.c
VGMPlay/chips/ay8910.h
VGMPlay/chips/ay8910_opl.c
VGMPlay/chips/ay_intf.c
VGMPlay/chips/ay_intf.h
VGMPlay/chips/c140.c
VGMPlay/chips/c140.h
VGMPlay/chips/c352.c
VGMPlay/chips/c352.h
VGMPlay/chips/c6280.c
VGMPlay/chips/c6280.h
VGMPlay/chips/c6280intf.c
VGMPlay/chips/c6280intf.h
VGMPlay/chips/dac_control.c
VGMPlay/chips/dac_control.h
VGMPlay/chips/emu2149.c
VGMPlay/chips/emu2149.h
VGMPlay/chips/emu2413.c
VGMPlay/chips/emu2413.h
VGMPlay/chips/emutypes.h
VGMPlay/chips/es5503.c
VGMPlay/chips/es5503.h
VGMPlay/chips/es5506.c
VGMPlay/chips/es5506.h
VGMPlay/chips/fm.c
VGMPlay/chips/fm.h
VGMPlay/chips/fm2612.c
VGMPlay/chips/fmopl.c
VGMPlay/chips/fmopl.h
VGMPlay/chips/gb.c
VGMPlay/chips/gb.h
VGMPlay/chips/iremga20.c
VGMPlay/chips/iremga20.h
VGMPlay/chips/k051649.c
VGMPlay/chips/k051649.h
VGMPlay/chips/k053260.c
py_vgmplayer.egg-info/PKG-INFO
py_vgmplayer.egg-info/SOURCES.txt
py_vgmplayer.egg-info/dependency_links.txt
py_vgmplayer.egg-info/not-zip-safe
py_vgmplayer.egg-info/top_level.txt
