Metadata-Version: 1.1
Name: py-vgmplayer
Version: 0.1.4
Summary: A Python library to play VGM files
Home-page: https://github.com/cecton/py-vgmplayer
Author: Cecile Tonglet
Author-email: cecile.tonglet@gmail.com
License: GPLv2
Platform: UNKNOWN
Classifier: Development Status :: 1 - Planning
Classifier: Intended Audience :: Developers
Classifier: Natural Language :: English
Classifier: License :: OSI Approved :: GNU General Public License v2 (GPLv2)
Classifier: Programming Language :: Python
Classifier: Programming Language :: Python :: 2.7
Classifier: Programming Language :: Python :: 3
Classifier: Programming Language :: Python :: 3.3
Classifier: Programming Language :: Python :: 3.4
Classifier: Programming Language :: Python :: 3.5
